MANIFEST.in
README.rst
setup.py
django_addon/__init__.py
django_addon/addon_config.py
django_addon/addon_form.py
django_addon/cli.py
django_addon/context_processors.py
django_addon/i18n_urls.py
django_addon/middleware.py
django_addon/models.py
django_addon/startup.py
django_addon/storage.py
django_addon/urls_redirect.py
django_addon/utils.py
django_addon.egg-info/PKG-INFO
django_addon.egg-info/SOURCES.txt
django_addon.egg-info/dependency_links.txt
django_addon.egg-info/entry_points.txt
django_addon.egg-info/not-zip-safe
django_addon.egg-info/requires.txt
django_addon.egg-info/top_level.txt
django_addon/management/__init__.py
django_addon/management/commands/__init__.py
django_addon/management/commands/aldryn_collectstatic.py
django_addon/management/commands/aldryn_optimize_static_images.py
django_addon/management/commands/aldryn_update_s3_media_headers.py
django_addon/monkeypatches/__init__.py
django_addon/monkeypatches/hide_secrets_in_debug_mode.py