Metadata-Version: 1.1
Name: django-addon
Version: 2.0.8.1
Summary: An opinionated Django setup bundled as an Addon
Home-page: https://github.com/django-addons/django-addon
Author: Divio AG
Author-email: info@divio.ch
License: UNKNOWN
Platform: UNKNOWN
Classifier: Development Status :: 2 - Pre-Alpha
Classifier: Programming Language :: Python :: 3.6
Classifier: Framework :: Django :: 2.0
